prompter/__init__.py
prompter/customexceptions.py
prompter/prompter.py
prompter/data/data.json
prompter/data/data.json.original
prompter_r3ap3rpy-0.1.9.dist-info/METADATA
prompter_r3ap3rpy-0.1.9.dist-info/WHEEL
prompter_r3ap3rpy-0.1.9.dist-info/top_level.txt
prompter_r3ap3rpy-0.1.9.dist-info/RECORD
