Metadata-Version: 2.4
Name: prompter-r3ap3rpy
Version: 0.1.9
Summary: Prompt your text-to-image AI
Home-page: https://pypi.org/project/prompter-r3ap3rpy/
Author: Szabó Dániel Ernő
Author-email: r3ap3rpy@gmail.com
License: MIT
Classifier: Programming Language :: Python :: 3.10
Classifier: License :: OSI Approved :: MIT License
Classifier: Operating System :: OS Independent
Requires-Python: >=3.10.0
Dynamic: author
Dynamic: author-email
Dynamic: classifier
Dynamic: description
Dynamic: description-content-type
Dynamic: home-page
Dynamic: license
Dynamic: requires-python
Dynamic: summary
